setup.py
dsnd_probability_acm/Binomialdistribution.py
dsnd_probability_acm/Gaussiandistribution.py
dsnd_probability_acm/Generaldistribution.py
dsnd_probability_acm/__init__.py
dsnd_probability_acm.egg-info/PKG-INFO
dsnd_probability_acm.egg-info/SOURCES.txt
dsnd_probability_acm.egg-info/dependency_links.txt
dsnd_probability_acm.egg-info/not-zip-safe
dsnd_probability_acm.egg-info/requires.txt
dsnd_probability_acm.egg-info/top_level.txt